<T3DataStructure>
	<meta>
		<langDisable>1</langDisable>
	</meta>
	<sheets>
		<lg>
			<ROOT>
				<type>array</type>
				<TCEforms>
					<sheetTitle>Col-lg-* options (# of columns 12)</sheetTitle>
				</TCEforms>
				<el>
					<lg_one>
						<TCEforms type="array">
							<label>LLL:EXT:t3sbootstrap/Resources/Private/Language/locallang_be.xlf:gridelement.anyColumns.colPos.0</label>
							<config>
								<type>input</type>
								<size>4</size>
								<max>2</max>
								<default>6</default>
								<eval>int</eval>
								<checkbox>0</checkbox>
							</config>
						</TCEforms>
					</lg_one>
					<lg_two>
						<TCEforms type="array">
							<label>LLL:EXT:t3sbootstrap/Resources/Private/Language/locallang_be.xlf:gridelement.anyColumns.colPos.1</label>
							<config>
								<type>input</type>
								<size>4</size>
								<max>2</max>
								<default>6</default>
								<eval>int</eval>
								<checkbox>0</checkbox>
							</config>
						</TCEforms>
					</lg_two>
				</el>
			</ROOT>
		</lg>
		<md>
			<ROOT>
				<type>array</type>
				<TCEforms>
					<sheetTitle>Col-md-* options</sheetTitle>
				</TCEforms>
				<el>
					<md_one>
						<TCEforms type="array">
							<label>LLL:EXT:t3sbootstrap/Resources/Private/Language/locallang_be.xlf:gridelement.anyColumns.colPos.0</label>
							<config>
								<type>input</type>
								<size>4</size>
								<max>2</max>
								<default>6</default>
								<eval>int</eval>
								<checkbox>0</checkbox>
							</config>
						</TCEforms>
					</md_one>
					<md_two>
						<TCEforms type="array">
							<label>LLL:EXT:t3sbootstrap/Resources/Private/Language/locallang_be.xlf:gridelement.anyColumns.colPos.1</label>
							<config>
								<type>input</type>
								<size>4</size>
								<max>2</max>
								<default>6</default>
								<eval>int</eval>
								<checkbox>0</checkbox>
							</config>
						</TCEforms>
					</md_two>
				</el>
			</ROOT>
		</md>
		<sm>
			<ROOT>
				<type>array</type>
				<TCEforms>
					<sheetTitle>Col-sm-* options</sheetTitle>
				</TCEforms>
				<el>
					<sm_one>
						<TCEforms type="array">
							<label>LLL:EXT:t3sbootstrap/Resources/Private/Language/locallang_be.xlf:gridelement.anyColumns.colPos.0</label>
							<config>
								<type>input</type>
								<size>4</size>
								<max>2</max>
								<default>6</default>
								<eval>int</eval>
								<checkbox>0</checkbox>
							</config>
						</TCEforms>
					</sm_one>
					<sm_two>
						<TCEforms type="array">
							<label>LLL:EXT:t3sbootstrap/Resources/Private/Language/locallang_be.xlf:gridelement.anyColumns.colPos.1</label>
							<config>
								<type>input</type>
								<size>4</size>
								<max>2</max>
								<default>6</default>
								<eval>int</eval>
								<checkbox>0</checkbox>
							</config>
						</TCEforms>
					</sm_two>
				</el>
			</ROOT>
		</sm>
		<xs>
			<ROOT>
				<type>array</type>
				<TCEforms>
					<sheetTitle>Col-xs-* options</sheetTitle>
				</TCEforms>
				<el>
					<xs_one>
						<TCEforms type="array">
							<label>LLL:EXT:t3sbootstrap/Resources/Private/Language/locallang_be.xlf:gridelement.anyColumns.colPos.0</label>
							<config>
								<type>input</type>
								<size>4</size>
								<max>2</max>
								<default>12</default>
								<eval>int</eval>
								<checkbox>0</checkbox>
							</config>
						</TCEforms>
					</xs_one>
					<xs_two>
						<TCEforms type="array">
							<label>LLL:EXT:t3sbootstrap/Resources/Private/Language/locallang_be.xlf:gridelement.anyColumns.colPos.1</label>
							<config>
								<type>input</type>
								<size>4</size>
								<max>2</max>
								<default>12</default>
								<eval>int</eval>
								<checkbox>0</checkbox>
							</config>
						</TCEforms>
					</xs_two>
				</el>
			</ROOT>
		</xs>
		<bgColor>
			<ROOT>
				<type>array</type>
				<TCEforms>
					<sheetTitle>Background-color</sheetTitle>
				</TCEforms>
                <type>array</type>
				<el>
					<bg_one>
						<TCEforms>
							<label>Background-color column 1</label>
							<config>
								<type>input</type>
								<size>4</size>
								<max>30</max>
								<checkbox>0</checkbox>
							</config>
						</TCEforms>
					</bg_one>
					<bg_two>
						<TCEforms>
							<label>Background-color column 2</label>
							<config>
								<type>input</type>
								<size>4</size>
								<max>30</max>
								<checkbox>0</checkbox>
							</config>
						</TCEforms>
					</bg_two>
				</el>
			</ROOT>
		</bgColor>
	</sheets>
</T3DataStructure>